Workbook

Sheet Calculator
A1: Educational tool, not tax advice. 2026 tax year, single filer, federal income tax only. Verify against the Sources tab before relying on it.
A3: YOUR NUMBERS
A4: Gross annual salary | C4: 75000 | D4: ← type your salary here
A5: Filing status | C5: Single
A6: Tax year | C6: 2026
A8: RESULTS
A9: Standard deduction | C9: =Rates!$B$13
A10: Taxable income | C10: =MAX(0,$C$4-$C$9)
A11: Total federal income tax | C11: =SUM($F$18:$F$24)
A12: Effective rate (on gross salary) | C12: =IF($C$4=0,0,$C$11/$C$4) | D12: ← what you actually pay
A13: Effective rate (on taxable income) | C13: =IF($C$10=0,0,$C$11/$C$10)
A14: Marginal rate (top bracket reached) | C14: =IF($C$10<=0,0,INDEX($D$18:$D$24,SUMPRODUCT(--($E$18:$E$24>0)))) | D14: ← the bracket people confuse it with
A16: BRACKET BY BRACKET
A17: Bracket | B17: From | C17: To | D17: Rate | E17: Income taxed here | F17: Tax
A18: 1 | B18: =Rates!$B$4 | C18: =IF(Rates!$C$4>=1E+12,"and above",Rates!$C$4) | D18: =Rates!$D$4 | E18: =MAX(0,MIN($C$10,Rates!$C$4)-Rates!$B$4) | F18: =$E18*$D18
A19: 2 | B19: =Rates!$B$5 | C19: =IF(Rates!$C$5>=1E+12,"and above",Rates!$C$5) | D19: =Rates!$D$5 | E19: =MAX(0,MIN($C$10,Rates!$C$5)-Rates!$B$5) | F19: =$E19*$D19
A20: 3 | B20: =Rates!$B$6 | C20: =IF(Rates!$C$6>=1E+12,"and above",Rates!$C$6) | D20: =Rates!$D$6 | E20: =MAX(0,MIN($C$10,Rates!$C$6)-Rates!$B$6) | F20: =$E20*$D20
A21: 4 | B21: =Rates!$B$7 | C21: =IF(Rates!$C$7>=1E+12,"and above",Rates!$C$7) | D21: =Rates!$D$7 | E21: =MAX(0,MIN($C$10,Rates!$C$7)-Rates!$B$7) | F21: =$E21*$D21
A22: 5 | B22: =Rates!$B$8 | C22: =IF(Rates!$C$8>=1E+12,"and above",Rates!$C$8) | D22: =Rates!$D$8 | E22: =MAX(0,MIN($C$10,Rates!$C$8)-Rates!$B$8) | F22: =$E22*$D22
A23: 6 | B23: =Rates!$B$9 | C23: =IF(Rates!$C$9>=1E+12,"and above",Rates!$C$9) | D23: =Rates!$D$9 | E23: =MAX(0,MIN($C$10,Rates!$C$9)-Rates!$B$9) | F23: =$E23*$D23
A24: 7 | B24: =Rates!$B$10 | C24: =IF(Rates!$C$10>=1E+12,"and above",Rates!$C$10) | D24: =Rates!$D$10 | E24: =MAX(0,MIN($C$10,Rates!$C$10)-Rates!$B$10) | F24: =$E24*$D24
E25: TOTAL | F25: =SUM($F$18:$F$24)
A27: Only the slice of income inside a bracket is taxed at that bracket's rate. Dollars in lower brackets keep their lower rate.

Sheet Rates
A1: 2026 TAX YEAR — SINGLE FILER
A2: Applies to TAXABLE income (after the standard deduction), not to gross salary.
A3: Bracket | B3: From | C3: To | D3: Rate
A4: 1 | B4: 0 | C4: 12400 | D4: 0.1
A5: 2 | B5: 12400 | C5: 50400 | D5: 0.12
A6: 3 | B6: 50400 | C6: 105700 | D6: 0.22
A7: 4 | B7: 105700 | C7: 201775 | D7: 0.24
A8: 5 | B8: 201775 | C8: 256225 | D8: 0.32
A9: 6 | B9: 256225 | C9: 640600 | D9: 0.35
A10: 7 | B10: 640600 | C10: 1000000000000 | D10: 0.37
A13: Standard deduction — Single | B13: 16100
A15: Figures change every year. Before reusing this file for another tax year, check the Sources tab and re-read them at irs.gov.

Sheet Sources
A1: PRIMARY SOURCES — every figure in this file
A3: Item | B3: Source | C3: Reference | D3: URL | E3: Date checked
A4: 2026 tax rate schedules (single) | B4: IRS | C4: IR-2025-103 / Rev. Proc. 2025-32 | D4: https://www.irs.gov/newsroom/irs-releases-tax-inflation-adjustments-for-tax-year-2026-including-amendments-from-the-one-big-beautiful-bill | E4: 2026-09-15
A5: 2026 standard deduction (single) | B5: IRS | C5: IR-2025-103 / Rev. Proc. 2025-32 | D5: https://www.irs.gov/newsroom/irs-releases-tax-inflation-adjustments-for-tax-year-2026-including-amendments-from-the-one-big-beautiful-bill | E5: 2026-09-15
A6: Premium Tax Credit — 400% FPL ceiling | B6: IRS | C6: FS-2025-10, Q7 (updated Feb. 19, 2026) | D6: https://www.irs.gov/affordable-care-act/individuals-and-families/questions-and-answers-on-the-premium-tax-credit | E6: 2026-09-15
A9: Nothing here is sourced from a blog, a news site, or an AI. Every number was read on the issuing agency's own page.
