Workbook

Sheet Calculator
A1: Educational tool, not financial or credit advice. It models one number — the balance your card reports — not your credit score. No model publishes a point-by-point scale, and this file does not invent one.
A3: YOUR NUMBERS
A4: Total credit limit, all cards | C4: 3000 | D4: ← fill the five amber cells
A5: What you charge in a month | C5: 2400
A6: Left on the statement on purpose | C6: 100 | D6: scenario B only. Set to 0 to report a zero balance — see row 32
A7: Statement closing day | C7: 3 | D7: on your statement, required by Regulation Z 1026.7(b)(10)
A8: Payment due day | C8: 28 | D8: this is NOT the date that matters for what gets reported
A10: SAME SPENDING, SAME MONEY PAID, TWO PAYMENT DATES
B11: A · pay after the close | D11: B · pay before the close
A12: Charged this month | B12: =$C$5 | D12: =$C$5
A13: Paid BEFORE the closing day | B13: 0 | D13: =MAX(0,$C$5-$C$6)
A14: =Balance on the closing day | B14: =MAX(0,$B$12-$B$13) | D14: =MAX(0,$D$12-$D$13) | E14: ← this is the number your card reports
A15: Reported utilization | B15: =IF($C$4=0,0,$B$14/$C$4) | D15: =IF($C$4=0,0,$D$14/$C$4)
A16: Against the 30% guideline | B16: =IF($B$15>Factors!$B$12,"over","under") | D16: =IF($D$15>Factors!$B$12,"over","under")
A18: Paid in full by the due date? | B18: yes | D18: yes
A19: Total paid over the month | B19: =$B$12 | D19: =$D$12 | E19: ← identical. The only difference between A and B is the date.
A20: Interest paid | B20: 0 | D20: 0
A22: Difference in reported utilization | C22: =$B$15-$D$15
A24: WHAT GETS REPORTED, FOR EVERY AMOUNT YOU LEAVE ON THE STATEMENT
A25: Left on the statement | B25: Reported balance | C25: Utilization | D25: vs the 30% guideline
A26: 0 | B26: =MIN($A26,$C$5) | C26: =IF($C$4=0,0,$B26/$C$4) | D26: =IF($C26>Factors!$B$12,"over","under")
A27: 100 | B27: =MIN($A27,$C$5) | C27: =IF($C$4=0,0,$B27/$C$4) | D27: =IF($C27>Factors!$B$12,"over","under")
A28: 300 | B28: =MIN($A28,$C$5) | C28: =IF($C$4=0,0,$B28/$C$4) | D28: =IF($C28>Factors!$B$12,"over","under")
A29: 600 | B29: =MIN($A29,$C$5) | C29: =IF($C$4=0,0,$B29/$C$4) | D29: =IF($C29>Factors!$B$12,"over","under")
A30: 900 | B30: =MIN($A30,$C$5) | C30: =IF($C$4=0,0,$B30/$C$4) | D30: =IF($C30>Factors!$B$12,"over","under")
A31: 1200 | B31: =MIN($A31,$C$5) | C31: =IF($C$4=0,0,$B31/$C$4) | D31: =IF($C31>Factors!$B$12,"over","under")
A32: 1800 | B32: =MIN($A32,$C$5) | C32: =IF($C$4=0,0,$B32/$C$4) | D32: =IF($C32>Factors!$B$12,"over","under")
A33: 2400 | B33: =MIN($A33,$C$5) | C33: =IF($C$4=0,0,$B33/$C$4) | D33: =IF($C33>Factors!$B$12,"over","under")
A34: The honest caveat, in FICO's own words
A35: "In some cases, a low credit utilization ratio will have a more positive impact on your FICO Scores than not using any of your available credit at all." — FICO, Amounts owed
A36: And the one that matters more: "You don't need to carry a balance on credit cards to get a good score. In fact, you don't need outstanding debt at all." — CFPB. Paying before the closing date is still paying in full. It costs no interest.

Sheet Factors
A1: WHAT A FICO SCORE IS MADE OF
A2: Category | B2: Weight | C2: What it covers
A3: Payment history | B3: 0.35 | C3: Do you pay on time. Not what this file is about.
A4: Amounts owed | B4: 0.3 | C4: Where credit utilization lives. This file models this line.
A5: Length of credit history | B5: 0.15 | C5: How long your accounts have been open.
A6: Credit mix | B6: 0.1 | C6: Cards, loans, mortgages.
A7: New credit | B7: 0.1 | C7: Recently opened accounts and hard inquiries.
A8: Total | B8: =SUM($B$3:$B$7) | C8: source: FICO, What's in my FICO Scores
A10: THE GUIDELINE USED BY THIS FILE
A11: Utilization guideline
A12: No more than | B12: 0.3
A14: CFPB: "Experts advise keeping your use of credit at no more than 30 percent of your total credit limit." This is guidance, not a threshold inside any scoring model. No source describes a cliff at 30%, and this file does not treat it as one.
A16: WHAT THIS FILE DOES NOT MODEL
A17: • Your credit score. This file models a reported balance, nothing else.
A18: • Points gained or lost. No scoring model publishes a point-by-point scale.
A19: • Per-card utilization. Some models look at each card as well as the total.
A20: • Your issuer's exact reporting day. FICO says 'typically' the latest statement balance; issuers vary, and some report off-cycle.
A21: • Any score other than FICO. VantageScore weighs things differently.

Sheet Sources
A1: EVERY FIGURE IN THIS FILE, AND WHERE IT COMES FROM
A2: What | B2: Who | C2: Reference | D2: URL | E2: Checked
A3: The balance on your credit report is the one your lender reported, typically your latest statement balance | B3: FICO | C3: Amounts owed | D3: https://www.myfico.com/credit-education/credit-scores/amount-of-debt | E3: 2026-09-24
A4: Amounts owed determines 30% of a FICO Score | B4: FICO | C4: Amounts owed | D4: https://www.myfico.com/credit-education/credit-scores/amount-of-debt | E4: 2026-09-24
A5: The five FICO categories and their weights | B5: FICO | C5: What's in my FICO Scores | D5: https://www.myfico.com/credit-education/whats-in-your-credit-score | E5: 2026-09-24
A6: A statement must show the closing date of the billing cycle and the balance outstanding on that date | B6: CFPB | C6: Regulation Z, 12 CFR 1026.7(b)(10) | D6: https://www.consumerfinance.gov/rules-policy/regulations/1026/7/ | E6: 2026-09-24
A7: Utilization = balances divided by limits; experts advise no more than 30% | B7: CFPB | C7: How do I get and keep a good credit score? | D7: https://www.consumerfinance.gov/ask-cfpb/how-do-i-get-and-keep-a-good-credit-score-en-318/ | E7: 2026-09-24
A8: You do not need to carry a balance to get a good score | B8: CFPB | C8: Credit score myths (myth 4) | D8: https://www.consumerfinance.gov/about-us/blog/credit-score-myths-might-be-holding-you-back-improving-your-credit/ | E8: 2026-09-24
A10: Rule of this channel
A11: Every number is read on the page of the organisation that issues the rule, or that produces the scoring model. Never a blog, a news site, another video, or an AI. If a figure is not on this tab, it is not in the video either.
